qlcore/__init__.py
qlcore/bootstrap.py
qlcore/builders.py
qlcore/config.py
qlcore/health.py
qlcore/helpers.py
qlcore/hooks.py
qlcore/pandas_ext.py
qlcore/presets.py
qlcore/py.typed
qlcore/shortcuts.py
qlcore/validators.py
qlcore/core/__init__.py
qlcore/core/constants.py
qlcore/core/enums.py
qlcore/core/exceptions.py
qlcore/core/protocols.py
qlcore/core/types.py
qlcore/data/__init__.py
qlcore/data/candle.py
qlcore/data/funding.py
qlcore/data/orderbook.py
qlcore/data/trade.py
qlcore/events/__init__.py
qlcore/events/fee.py
qlcore/events/fill.py
qlcore/events/funding.py
qlcore/events/liquidation.py
qlcore/events/settlement.py
qlcore/fees/__init__.py
qlcore/fees/calculator.py
qlcore/fees/funding.py
qlcore/fees/tiers.py
qlcore/fees/trading.py
qlcore/instruments/__init__.py
qlcore/instruments/base.py
qlcore/instruments/futures.py
qlcore/instruments/options.py
qlcore/instruments/perpetual.py
qlcore/instruments/specs.py
qlcore/instruments/spot.py
qlcore/margin/__init__.py
qlcore/margin/cross.py
qlcore/margin/isolated.py
qlcore/margin/requirements.py
qlcore/margin/utilization.py
qlcore/math/__init__.py
qlcore/math/precision.py
qlcore/math/returns.py
qlcore/math/rounding.py
qlcore/math/stats.py
qlcore/math/volatility.py
qlcore/monitoring/__init__.py
qlcore/monitoring/metrics.py
qlcore/monitoring/performance.py
qlcore/orders/__init__.py
qlcore/orders/base.py
qlcore/orders/conditions.py
qlcore/orders/state.py
qlcore/orders/types/__init__.py
qlcore/orders/types/iceberg.py
qlcore/orders/types/limit.py
qlcore/orders/types/market.py
qlcore/orders/types/stop_limit.py
qlcore/orders/types/stop_market.py
qlcore/orders/types/trailing_stop.py
qlcore/pnl/__init__.py
qlcore/pnl/attribution.py
qlcore/pnl/calculator.py
qlcore/pnl/funding.py
qlcore/pnl/realized.py
qlcore/pnl/unrealized.py
qlcore/portfolio/__init__.py
qlcore/portfolio/account.py
qlcore/portfolio/allocation.py
qlcore/portfolio/ledger.py
qlcore/portfolio/portfolio.py
qlcore/positions/__init__.py
qlcore/positions/base.py
qlcore_lib-0.4.0.dist-info/licenses/LICENSE
qlcore_lib-0.4.0.dist-info/METADATA
qlcore_lib-0.4.0.dist-info/WHEEL
qlcore_lib-0.4.0.dist-info/top_level.txt
qlcore_lib-0.4.0.dist-info/RECORD
