Metadata-Version: 2.4
Name: qlcore-lib
Version: 0.4.0
Summary: Pure trading math and domain models: orders, positions, portfolio, PnL, sizing, risk.
Author: ZENTCH-Q
License: MIT
Project-URL: Documentation, https://zentch-q.github.io/qlcore-docs/
Project-URL: Repository, https://github.com/ZENTCH-Q/qldata-docs/tree/main
Classifier: License :: OSI Approved :: MIT License
Classifier: Programming Language :: Python
Classifier: Programming Language :: Python :: 3
Classifier: Programming Language :: Python :: 3.11
Classifier: Intended Audience :: Financial and Insurance Industry
Classifier: Topic :: Office/Business :: Financial :: Investment
Classifier: Development Status :: 3 - Alpha
Requires-Python: >=3.11
License-File: LICENSE
Provides-Extra: dev
Requires-Dist: pytest; extra == "dev"
Requires-Dist: pytest-cov; extra == "dev"
Requires-Dist: ruff; extra == "dev"
Requires-Dist: black; extra == "dev"
Requires-Dist: mypy; extra == "dev"
Provides-Extra: monitoring
Requires-Dist: psutil>=5.9.0; extra == "monitoring"
Dynamic: license-file
